[
  {
    "username": "Jovan123",
    "date_time": "2023-07-03T23:05:55.757238800"
  },
  {
    "username": "Jovan123",
    "date_time": "2022-07-03T23:06:12.033185700"
  },
  {
    "username": "Jovan123",
    "date_time": "2023-07-03T23:06:13.221682500"
  },
  {
    "username": "Jovan123",
    "date_time": "2023-07-03T23:28:32.778309"
  },
  {
    "username": "Nesto123",
    "date_time": "2023-07-03T23:05:55.757238800"
  },
  {
    "username": "Nesto123",
    "date_time": "2023-07-03T23:06:12.033185700"
  },
  {
    "username": "Nesto123",
    "date_time": "2023-07-03T23:06:13.221682500"
  }
]